wheniwork/__init__.py
wheniwork/version.py
wheniwork-0.2.0.dist-info/LICENSE
wheniwork-0.2.0.dist-info/LICENSE.txt
wheniwork-0.2.0.dist-info/METADATA
wheniwork-0.2.0.dist-info/WHEEL
wheniwork-0.2.0.dist-info/top_level.txt
wheniwork-0.2.0.dist-info/RECORD
