Metadata-Version: 2.1
Name: wheniwork
Version: 0.2.0
Summary: A library for interfacing with the WhenIWork.com API
Home-page: https://github.com/fimion/wheniwork-api-py
Author: Alex Riviere
Author-email: fimion@gmail.com
License: MIT
Download-URL: https://github.com/fimion/wheniwork-api-py/tarball/0.2.0
Keywords: wheniwork,api
Platform: UNKNOWN
Requires-Dist: requests (==2.20.1)
